{
   "entities":[
      {
         "matched_in":"Bonsai Stonecrop",
         "matched_in_type":"common_name",
         "access_token":"XGhTahdxPloZeH5HMlQAM1NkRXZWY1cyB2QeegQyTHk-",
         "match_position":0,
         "match_length":6,
         "entity_name":"Crassula sarcocaulis"
      },
      {
         "matched_in":"bonsai tree",
         "matched_in_type":"common_name",
         "access_token":"XGhdakFxY1pPeHNHMVRSM1xkQHZWYwoyU2RNelAyTXk-",
         "match_position":0,
         "match_length":6,
         "entity_name":"Pinus parviflora"
      },
      {
         "matched_in":"Bonsai Mint",
         "matched_in_type":"common_name",
         "access_token":"C2hfahRxblpPeHJHYVQKM1dkR3ZXY1YyV2QeegMyG3k-",
         "match_position":0,
         "match_length":6,
         "entity_name":"Plectranthus ernstii"
      }
   ],
   "entities_trimmed":false,
   "limit":10
}
